setup.cfg
setup.py
copybookda/__init__.py
copybookda.egg-info/PKG-INFO
copybookda.egg-info/SOURCES.txt
copybookda.egg-info/dependency_links.txt
copybookda.egg-info/requires.txt
copybookda.egg-info/top_level.txt